csvputty/__init__.py
csvputty/__main__.py
csvputty/diff.py
csvputty/markup.py
csvputty/rm.py
csvputty-0.1.0.dist-info/DESCRIPTION.rst
csvputty-0.1.0.dist-info/METADATA
csvputty-0.1.0.dist-info/RECORD
csvputty-0.1.0.dist-info/WHEEL
csvputty-0.1.0.dist-info/entry_points.txt
csvputty-0.1.0.dist-info/metadata.json
csvputty-0.1.0.dist-info/top_level.txt
