Metadata-Version: 2.0
Name: csvputty
Version: 0.1.0
Summary: CSV CLI utility functions and packages in Python.
Home-page: https://github.com/Antman261/csvputty
Author: Anthony Manning-Franklin
Author-email: anthony.manning.franklin@gmail.com
License: MIT
Keywords: csv command line cli
Platform: UNKNOWN
Classifier: Intended Audience :: Developers
Classifier: License :: OSI Approved :: MIT License
Classifier: Programming Language :: Python :: 3
Classifier: Programming Language :: Python :: 3.1
Classifier: Programming Language :: Python :: 3.2
Classifier: Programming Language :: Python :: 3.3
Classifier: Programming Language :: Python :: 3.4
Classifier: Programming Language :: Python :: 3.5
Requires-Dist: Click
